datapulse/__init__.py
datapulse/data/__init__.py
datapulse/data/continousdata.py
datapulse/data/data.py
datapulse/data/staticdata.py
datapulse/dataprocessing/__init__.py
datapulse/dataprocessing/datacleaning.py
datapulse/dataprocessing/datatransform.py
datapulse/dataprocessing/cleaning/__init__.py
datapulse/dataprocessing/cleaning/continuouscleaning.py
datapulse/dataprocessing/cleaning/staticcleaning.py
datapulse/dataprocessing/transform/__init__.py
datapulse/dataprocessing/transform/continuoustransform.py
datapulse/dataprocessing/transform/statictransform.py
datapulse/datasource/__init__.py
datapulse/datasource/continoussource.py
datapulse/datasource/datasource.py
datapulse/datasource/staticsource.py
datapulse/datasource/continuous/__init__.py
datapulse/datasource/continuous/sensor.py
datapulse/datasource/static/__init__.py
datapulse/datasource/static/csv.py
datapulse/datasource/static/nosql.py
datapulse/datasource/static/sql.py
datapulse/logs/__init__.py
datapulse/logs/error_handling/__init__.py
datapulse/logs/error_handling/custom_exceptions.py
datapulse/logs/logging/__init__.py
datapulse/logs/logging/logger_config.py
datapulse/pipeline/__init__.py
datapulse/pipeline/continuouspipeline.py
datapulse/pipeline/pipeline.py
datapulse/pipeline/staticpipeline.py
datapulse/tools/__init__.py
datapulse/ui/desktop/__init__.py
datapulse/ui/desktop/about_window.py
datapulse/ui/desktop/main_window.py
datapulse/ui/desktop/setting_window.py
datapulse/ui/web/__init__.py
datapulse/ui/web/structure idea.md
datapulse/visualization/__init__.py
datapulse/visualization/plot.py
datapulse/visualization/tab.py
datapulse/visualization/plots/__init__.py
datapulse/visualization/plots/bar_chart.py
datapulse/visualization/plots/calendar_chart.py
datapulse/visualization/plots/line_chart.py
datapulse/visualization/plots/pie_chart.py
datapulse/visualization/plots/scatter_plot.py
datapulse/visualization/tabs/__init__.py
datapulse-0.0.1.dist-info/METADATA
datapulse-0.0.1.dist-info/WHEEL
datapulse-0.0.1.dist-info/RECORD
